xepmts_server/__init__.py
xepmts_server/admin/__init__.py
xepmts_server/admin/app.py
xepmts_server/admin/settings.py
xepmts_server/cli.py
xepmts_server/sc/app.py
xepmts_server/sc/config.py
xepmts_server/sc/settings.py
xepmts_server/secrets.py
xepmts_server/server.py
xepmts_server/utils.py
xepmts_server/v1/__init__.py
xepmts_server/v1/app.py
xepmts_server/v1/auth.py
xepmts_server/v1/client.py
xepmts_server/v1/domain.py
xepmts_server/v1/settings.py
xepmts_server/v2/__init__.py
xepmts_server/v2/app.py
xepmts_server/v2/client.py
xepmts_server/v2/domain.py
xepmts_server/v2/roles.py
xepmts_server/v2/settings.py
xepmts_server/v2/utils.py
xepmts_server/versions/__init__.py
xepmts_server-0.1.12.dist-info/entry_points.txt
xepmts_server-0.1.12.dist-info/LICENSE
xepmts_server-0.1.12.dist-info/WHEEL
xepmts_server-0.1.12.dist-info/METADATA
xepmts_server-0.1.12.dist-info/RECORD
